torch_lr_finder/__init__.py
torch_lr_finder/lr_finder.py
torch_lr_finder-0.2.2.dist-info/LICENSE
torch_lr_finder-0.2.2.dist-info/METADATA
torch_lr_finder-0.2.2.dist-info/WHEEL
torch_lr_finder-0.2.2.dist-info/top_level.txt
torch_lr_finder-0.2.2.dist-info/RECORD
