Metadata-Version: 2.1
Name: torch-lr-finder
Version: 0.2.2
Summary: Pytorch implementation of the learning rate range test
Home-page: https://github.com/davidtvs/pytorch-lr-finder
Author: David Silva
Author-email: davidtvs10@gmail.com
Classifier: Programming Language :: Python
Classifier: License :: OSI Approved :: MIT License
Classifier: Intended Audience :: Developers
Classifier: Intended Audience :: Science/Research
Classifier: Intended Audience :: Education
Classifier: Topic :: Software Development
Classifier: Topic :: Scientific/Engineering :: Artificial Intelligence
Requires-Python: >=3.5.9
License-File: LICENSE
Requires-Dist: matplotlib
Requires-Dist: numpy
Requires-Dist: torch>=0.4.1
Requires-Dist: tqdm
Requires-Dist: packaging
Provides-Extra: tests
Requires-Dist: pytest; extra == "tests"
Requires-Dist: pytest-cov; extra == "tests"
Requires-Dist: pytest-mock; extra == "tests"
Provides-Extra: dev
Requires-Dist: pytest; extra == "dev"
Requires-Dist: pytest-cov; extra == "dev"
Requires-Dist: pytest-mock; extra == "dev"
Requires-Dist: flake8; extra == "dev"
Requires-Dist: black; extra == "dev"
Requires-Dist: pep8-naming; extra == "dev"
Requires-Dist: torchvision; extra == "dev"
Requires-Dist: ipywidgets; extra == "dev"
